turtle_pil/__init__.py
turtle_pil-1.1.2.dist-info/LICENSE
turtle_pil-1.1.2.dist-info/METADATA
turtle_pil-1.1.2.dist-info/WHEEL
turtle_pil-1.1.2.dist-info/entry_points.txt
turtle_pil-1.1.2.dist-info/top_level.txt
turtle_pil-1.1.2.dist-info/RECORD
