Metadata-Version: 2.1
Name: turtle-pil
Version: 1.1.2
Summary: Turtle operations on the top of PIL
Home-page: https://github.com/jutge-org/pil-turtle
Author: Jordi Petit
Author-email: UNKNOWN
License: Apache
Download-URL: https://github.com/jutge-org/pil-turtle/tarball/1.1.2
Keywords: jutge,jutge.org,education,turtle,PIL
Platform: UNKNOWN
Requires-Dist: pillow
